wvlet/__init__.py
wvlet/compiler.py
wvlet/libs/.gitkeep
wvlet/libs/darwin_arm64/.gitkeep
wvlet/libs/darwin_arm64/libwvlet.dylib
wvlet/libs/linux_aarch64/.gitkeep
wvlet/libs/linux_aarch64/libwvlet.so
wvlet/libs/linux_x86_64/.gitkeep
wvlet/libs/linux_x86_64/libwvlet.so
wvlet-2025.1.22.dist-info/METADATA
wvlet-2025.1.22.dist-info/WHEEL
wvlet-2025.1.22.dist-info/top_level.txt
wvlet-2025.1.22.dist-info/RECORD
