Metadata-Version: 2.4
Name: wvlet
Version: 2025.1.22
Summary: Python SDK for Wvlet - A flow-style query language
Author-email: "wvlet.org" <taro.saito@wvlet.org>
License: Apache-2.0
Project-URL: Homepage, https://wvlet.org/
Project-URL: Documentation, https://wvlet.org/
Project-URL: Repository, https://github.com/wvlet/wvlet
Project-URL: Issues, https://github.com/wvlet/wvlet/issues
Classifier: Development Status :: 3 - Alpha
Classifier: Intended Audience :: Developers
Classifier: License :: OSI Approved :: Apache Software License
Classifier: Operating System :: POSIX :: Linux
Classifier: Operating System :: MacOS :: MacOS X
Classifier: Programming Language :: Python :: 3
Classifier: Programming Language :: Python :: 3.9
Classifier: Programming Language :: Python :: 3.10
Classifier: Programming Language :: Python :: 3.11
Classifier: Programming Language :: Python :: 3.12
Classifier: Programming Language :: Python :: 3.13
Classifier: Topic :: Database
Classifier: Topic :: Software Development :: Compilers
Requires-Python: >=3.9
Provides-Extra: dev
Requires-Dist: pytest>=6.0; extra == "dev"
